eqodec/__init__.py
eqodec/carbon.py
eqodec/loss.py
eqodec/metric.py
eqodec-0.4.0.dist-info/METADATA
eqodec-0.4.0.dist-info/WHEEL
eqodec-0.4.0.dist-info/top_level.txt
eqodec-0.4.0.dist-info/RECORD
