Metadata-Version: 2.4
Name: eqodec
Version: 0.4.0
Author: Ian Jure Macalisang
Author-email: ianjuremacalisang2@gmail.com
Requires-Dist: torch>=2.0
Requires-Dist: codecarbon>=3.1.0
Requires-Dist: numpy
Dynamic: author
Dynamic: author-email
Dynamic: description
Dynamic: description-content-type
Dynamic: requires-dist
